README.rst
setup.py
pyjsonlines/__init__.py
pyjsonlines/pyjsonlines.py
pyjsonlines.egg-info/PKG-INFO
pyjsonlines.egg-info/SOURCES.txt
pyjsonlines.egg-info/dependency_links.txt
pyjsonlines.egg-info/requires.txt
pyjsonlines.egg-info/top_level.txt
pyjsonlines/tests/__init__.py