Metadata-Version: 1.1
Name: pyjsonlines
Version: 2.0.1
Summary: Library to convert Json to Jsonlines or ndjson and Jsonlines or ndjson to Json.
Home-page: https://github.com/thisischandanmishra/pyjsonlines
Author: Chandan Kumar
Author-email: devchandankumar2@gmail.com
License: MIT
Keywords: jsonl2json jsonlines json2jsonl pyndjson pyjsonlines
Platform: UNKNOWN
Classifier: Development Status :: 5 - Production/Stable
Classifier: Intended Audience :: Developers
Classifier: Intended Audience :: System Administrators
Classifier: License :: OSI Approved :: BSD License
Classifier: Programming Language :: Python
Classifier: Programming Language :: Python :: 2.7
Classifier: Programming Language :: Python :: 3
Classifier: Programming Language :: Python :: 3.4
Classifier: Programming Language :: Python :: 3.5
Classifier: Programming Language :: Python :: 3.6
Classifier: Programming Language :: Python :: 3.7
Classifier: Programming Language :: Python :: 3.8
Classifier: Topic :: Internet :: Log Analysis
Classifier: Topic :: Software Development :: Libraries :: Python Modules
Classifier: Topic :: System :: Logging
Classifier: Topic :: Utilities
